rwspider/__init__.py
rwspider-1.0.0.dist-info/METADATA
rwspider-1.0.0.dist-info/WHEEL
rwspider-1.0.0.dist-info/entry_points.txt
rwspider-1.0.0.dist-info/top_level.txt
rwspider-1.0.0.dist-info/RECORD
