Metadata-Version: 2.1
Name: rwspider
Version: 1.0.0
Summary: python 爬虫扩展功能
Home-page: https://ruiwencloud.xyz
Author: Rui Ma
Author-email: ruima_06@outlook.com
License: UNKNOWN
Platform: UNKNOWN
Requires-Dist: requests
